filefinder/__init__.py
filefinder/filters.py
filefinder/finder.py
filefinder/format.py
filefinder/group.py
filefinder/library.py
filefinder/matches.py
filefinder/py.typed
filefinder/util.py
filefinder-1.3.0.dist-info/LICENSE
filefinder-1.3.0.dist-info/METADATA
filefinder-1.3.0.dist-info/WHEEL
filefinder-1.3.0.dist-info/top_level.txt
filefinder-1.3.0.dist-info/RECORD
