Metadata-Version: 2.1
Name: filefinder
Version: 1.3.0
Summary: Find files using a simple syntax.
Author-email: Clément Haëck <clement.haeck@locean.ipsl.fr>
Project-URL: Source, https://github.com/Descanonge/filefinder
Project-URL: Documentation, https://filefinder.readthedocs.io
Classifier: Development Status :: 4 - Beta
Classifier: License :: OSI Approved :: MIT License
Classifier: Programming Language :: Python
Classifier: Programming Language :: Python :: 3 :: Only
Classifier: Programming Language :: Python :: 3.10
Classifier: Programming Language :: Python :: 3.11
Classifier: Operating System :: OS Independent
Classifier: Intended Audience :: Developers
Classifier: Intended Audience :: Science/Research
Classifier: Topic :: Utilities
Requires-Python: >=3.10
License-File: LICENSE
Provides-Extra: dev
Requires-Dist: sphinx ==6.2.1 ; extra == 'dev'
Requires-Dist: sphinx-book-theme ==1.0.1 ; extra == 'dev'
Requires-Dist: ruff ; extra == 'dev'
Requires-Dist: mypy >=1.5 ; extra == 'dev'
Requires-Dist: pytest >=7.4 ; extra == 'dev'
Requires-Dist: pyfakefs ; extra == 'dev'
Requires-Dist: hypothesis ; extra == 'dev'
Requires-Dist: coverage ; extra == 'dev'
Requires-Dist: pytest-cov ; extra == 'dev'
